multitrim/__init__.py
multitrim/multitrim.py
multitrim-1.2.6.dist-info/LICENSE
multitrim-1.2.6.dist-info/METADATA
multitrim-1.2.6.dist-info/WHEEL
multitrim-1.2.6.dist-info/entry_points.txt
multitrim-1.2.6.dist-info/top_level.txt
multitrim-1.2.6.dist-info/RECORD
