Metadata-Version: 2.1
Name: multitrim
Version: 1.2.6
Summary: A readtrimming and quality control pipeline
Home-page: https://github.com/KGerhardt/multitrim
Author: Kenji Gerhardt
Author-email: kenji.gerhardt@gmail.com
License: UNKNOWN
Platform: UNKNOWN
Requires-Python: >=3
